AES.c
AES.h
MANIFEST.in
_mpicrypt.c
bn_asm.h
jsalloc.h
md5.c
md5.h
mpi.c
mpi.h
platform.h
py_aescounter.c
py_keyobj.c
py_sha.c
randbytes.py
randpool.py
setup.py
sha1.c
sha1.h
starimpl.h
mpicrypt.egg-info/PKG-INFO
mpicrypt.egg-info/SOURCES.txt
mpicrypt.egg-info/dependency_links.txt
mpicrypt.egg-info/top_level.txt