Metadata-Version: 1.0
Name: mpicrypt
Version: 1.9
Summary: Python _mpicrypt helper
Home-page: UNKNOWN
Author: Jeff Senn
Author-email: jeffsenn@gmail.com
License: UNKNOWN
Platform: UNKNOWN
